scSLAT/__init__.py
scSLAT/metrics.py
scSLAT/model/__init__.py
scSLAT/model/batch.py
scSLAT/model/graphconv/__init__.py
scSLAT/model/graphconv/combnet.py
scSLAT/model/graphmodel.py
scSLAT/model/loaddata.py
scSLAT/model/prematch/__init__.py
scSLAT/model/prematch/icp.py
scSLAT/model/prematch/utils.py
scSLAT/model/preprocess.py
scSLAT/model/train.py
scSLAT/model/utils.py
scSLAT/utils.py
scSLAT/viz/__init__.py
scSLAT/viz/color.py
scSLAT/viz/multi_dataset.py
scslat-0.3.0.dist-info/LICENSE
scslat-0.3.0.dist-info/METADATA
scslat-0.3.0.dist-info/WHEEL
scslat-0.3.0.dist-info/entry_points.txt
scslat-0.3.0.dist-info/RECORD
