Metadata-Version: 2.1
Name: scSLAT
Version: 0.3.0
Summary: A graph deep learning based tool to align single cell spatial omics data
Home-page: https://github.com/gao-lab/SLAT
License: MIT
Keywords: bioinformatics,deep-learning,graph-neural-network,single-cell,spatial-omics
Author: Chen-Rui Xia
Author-email: xiachenrui@mail.cbi.pku.edu.cn
Requires-Python: >=3.8
Classifier: Intended Audience :: Science/Research
Classifier: License :: OSI Approved :: MIT License
Classifier: Natural Language :: English
Classifier: Operating System :: MacOS :: MacOS X
Classifier: Operating System :: Microsoft :: Windows
Classifier: Operating System :: POSIX :: Linux
Classifier: Programming Language :: Python :: 3
Classifier: Programming Language :: Python :: 3.8
Classifier: Programming Language :: Python :: 3.9
Classifier: Programming Language :: Python :: 3.10
Classifier: Programming Language :: Python :: 3.11
Classifier: Programming Language :: Python :: 3.12
Classifier: Programming Language :: Python :: 3.13
Classifier: Topic :: Scientific/Engineering :: Bio-Informatics
Provides-Extra: dev
Provides-Extra: docs
Requires-Dist: anndata (>0.9)
Requires-Dist: faiss-cpu
Requires-Dist: h5py
Requires-Dist: harmony-pytorch
Requires-Dist: harmonypy
Requires-Dist: ipython ; extra == "dev"
Requires-Dist: jinja2 ; extra == "docs"
Requires-Dist: joblib
Requires-Dist: jupyter ; extra == "dev"
Requires-Dist: kaleido
Requires-Dist: leidenalg
Requires-Dist: matplotlib (>3.1.2)
Requires-Dist: myst-parser ; extra == "docs"
Requires-Dist: nbformat ; extra == "dev"
Requires-Dist: nbsphinx ; extra == "docs"
Requires-Dist: numpy (>1.19,<2.0)
Requires-Dist: opencv-python
Requires-Dist: packaging
Requires-Dist: pandas (>1.1,<2.0)
Requires-Dist: papermill ; extra == "dev"
Requires-Dist: parse ; extra == "dev"
Requires-Dist: plotly
Requires-Dist: pre-commit ; extra == "dev"
Requires-Dist: pynvml
Requires-Dist: pytest ; extra == "dev"
Requires-Dist: pytest-cov ; extra == "dev"
Requires-Dist: pyyaml
Requires-Dist: scanpy (>1.9)
Requires-Dist: scikit-learn (>0.21.2)
Requires-Dist: scikit-misc
Requires-Dist: scipy (>1.3)
Requires-Dist: seaborn (>0.9)
Requires-Dist: sphinx (<=6.2.1) ; extra == "docs"
Requires-Dist: sphinx-autodoc-typehints ; extra == "docs"
Requires-Dist: sphinx-copybutton ; extra == "docs"
Requires-Dist: sphinx-intl ; extra == "docs"
Requires-Dist: sphinx-rtd-theme ; extra == "docs"
Requires-Dist: sphinx_gallery (>=0.8.2,<0.11) ; extra == "docs"
Requires-Dist: torch (>=2.0,<2.4)
Requires-Dist: torch_geometric (>=2.3.0,<2.6)
Requires-Dist: torchaudio
Requires-Dist: torchvision
Project-URL: Documentation, https://slat.readthedocs.io/en/latest/
Project-URL: Repository, https://github.com/gao-lab/SLAT
